Metadata-Version: 2.1
Name: odoo12-addon-l10n-it-account-tax-kind
Version: 12.0.2.1.1
Summary: Italian Localisation - Natura delle aliquote IVA
Home-page: https://github.com/OCA/l10n-italy/tree/12.0/l10n_it_account_tax_kind
Author: Odoo Community Association (OCA), Apulia Software s.r.l
Author-email: support@odoo-community.org
License: AGPL-3
Platform: UNKNOWN
Classifier: Programming Language :: Python
Classifier: Framework :: Odoo
Classifier: Framework :: Odoo :: 12.0
Classifier: License :: OSI Approved :: GNU Affero General Public License v3
Classifier: Development Status :: 5 - Production/Stable
Requires-Python: >=3.5
Requires-Dist: odoo12-addon-l10n-it-account
Requires-Dist: odoo <12.1dev,>=12.0a
